byword/__init__.py
byword/__main__.py
byword/core.py
byword-0.1.0.dist-info/LICENSE
byword-0.1.0.dist-info/METADATA
byword-0.1.0.dist-info/WHEEL
byword-0.1.0.dist-info/entry_points.txt
byword-0.1.0.dist-info/top_level.txt
byword-0.1.0.dist-info/RECORD
